kmedoids-0.5.4.dist-info/METADATA
kmedoids-0.5.4.dist-info/WHEEL
kmedoids-0.5.4.dist-info/licenses/LICENSE
kmedoids/__init__.py
kmedoids/kmedoids.cpython-311-darwin.so
kmedoids-0.5.4.dist-info/RECORD
