Metadata-Version: 2.3
Name: kmedoids
Version: 0.5.4
License-File: LICENSE
Summary: k-Medoids Clustering in Python with FasterPAM
Home-Page: https://github.com/kno10/python-kmedoids
Author: Erich Schubert <erich.schubert@tu-dortmund.de>, Lars Lenssen <lars.lenssen@tu-dortmund.de>
Author-email: Erich Schubert <erich.schubert@tu-dortmund.de>, Lars Lenssen <lars.lenssen@tu-dortmund.de>
License: GPL-3.0-or-later
Project-URL: Source Code, https://github.com/kno10/python-kmedoids
